sigdepsem/__init__.py
sigdepsem/main.py
sigdepsem-0.1.dist-info/LICENSE
sigdepsem-0.1.dist-info/WHEEL
sigdepsem-0.1.dist-info/METADATA
sigdepsem-0.1.dist-info/RECORD
